{
	"category": [
		{
			"cat-title": "Séries",
			"card": [
				{
					"image": "https://cdn.rawgit.com/Darxenas/mv-data/3346f24a62c2e1f8dd396d42f47f161f9e749d2f/images/punisher.jpg",
					"card-title": "Punisher",
					"card-description": "Hanté par l'assassinat de sa famille, l'ancien Marines Frank Castle devient un justicier connu dans le milieu criminel...",
					"tag": [
						"Action"
					]
				},
				{
					"image": "https://cdn.rawgit.com/Darxenas/mv-data/542c59a999364659a0d2c6d48a82b44d2549924c/images/cq5dam.web.1200.675%20(1).jpeg",
					"card-title": "Game of Thrones",
					"card-description": "Sur le continent de Westeros, le roi Robert Baratheon gouverne le Royaume des Sept Couronnes depuis plus de dix-sept ans...",
					"tag": [
						"Fantaisie"
					]
				},
				{
					"image": "https://cdn.rawgit.com/Darxenas/mv-data/49665ff5cd9e28c3827de4b225fc7b1d95e59b08/images/TBBT.jpg",
					"card-title": "The Big Bang Theory",
					"card-description": "Leonard Hofstadter et Sheldon Cooper vivent en colocation à Pasadena, ville de l'agglomération de Los Angeles. Ce sont tous deux des physiciens surdoués...",
					"tag": [
						"Sitcom"
					]
				}
			]
		},
		{
			"cat-title": "Jeux vidéo",
			"card": [
				{
					"image": "https://cdn.rawgit.com/Darxenas/mv-data/12d2f19e21c8b043b9f1b1f78fdb79e046db8062/images/h6v57xjriwwcpbqmdkxo.jpg",
					"card-title": "Kingdom Hearts II",
					"card-description": "Sora, Donald et Dingo sont restés inanimés pendant un an afin de retrouver, dans Chain of Memories, leurs souvenirs perdus. Pendant ce temps Roxas, le Simili de Sora, est pris au piège dans une simulation virtuelle...",
					"tag": [
						"Action-RPG"
					]
				},
				{
					"image": "https://cdn.rawgit.com/Darxenas/mv-data/49399c60e7d646b9ab779a6a77fed20df972ae0e/images/Nier-Automata-01.jpg",
					"card-title": "NieR: Automata",
					"card-description": "2B, 9S et A2 se battent contre des machines dans un monde post-apocalyptique. Envoyés par les humains, leur mission est de sauver l'humanité des machines...",
					"tag": [
						"Action-RPG"
					]
				},
				{
					"image": "https://cdn.rawgit.com/Darxenas/mv-data/d25b558d311b7161d375946f146f328c4bda2a59/images/tearaway-listing-thumb-02-psvita-us.png",
					"card-title": "Tearaway",
					"card-description": "L'histoire de Tearaway est celle d'un messager qui a pour mission de délivrer un message unique au joueur...",
					"tag": [
						"Action/Plate-formes"
					]
				}
			]
		},
		{
			"card": []
		}
	]
}