{
	"category": [
		{
			"cat-title": "Séries",
			"card": [
				{
					"image": "https://cdn.rawgit.com/Darxenas/mv-data/3346f24a62c2e1f8dd396d42f47f161f9e749d2f/images/punisher.jpg",
					"card-title": "Punisher",
					"card-description": "Hanté par l'assassinat de sa famille, l'ancien Marines Frank Castle devient un justicier connu dans le milieu criminel...",
					"tag": [
						"Action"
					]
				},
				{
					"image": "https://cdn.rawgit.com/Darxenas/mv-data/542c59a999364659a0d2c6d48a82b44d2549924c/images/cq5dam.web.1200.675%20(1).jpeg",
					"card-title": "Game of Thrones",
					"card-description": "Sur le continent de Westeros, le roi Robert Baratheon gouverne le Royaume des Sept Couronnes depuis plus de dix-sept ans...",
					"tag": [
						"Fantaisie"
					]
				},
				{
					"image": "https://cdn.rawgit.com/Darxenas/mv-data/49665ff5cd9e28c3827de4b225fc7b1d95e59b08/images/TBBT.jpg",
					"card-title": "The Big Bang Theory",
					"card-description": "Leonard Hofstadter et Sheldon Cooper vivent en colocation à Pasadena, ville de l'agglomération de Los Angeles. Ce sont tous deux des physiciens surdoués...",
					"tag": [
						"Sitcom"
					]
				}
			]
		},
		{
			"cat-title": "Jeux vidéo",
			"card": [
				{
					"image": "https://cdn.rawgit.com/Darxenas/mv-data/eca7eead575db4ee73dbc60af8f67265d67b181b/images/kingdom-hearts-ii-01b.jpg",
					"card-title": "Kingdom Hearts II",
					"card-description": "Sora, Donald et Dingo sont restés inanimés pendant un an afin de retrouver, dans Chain of Memories, leurs souvenirs perdus. Pendant ce temps Roxas, le Simili de Sora, est pris au piège dans une simulation virtuelle",
					"tag": [
						"Action-RPG"
					]
				}
			]
		}
	]
}